setup.py
slack_bot/__init__.py
slack_bot/slack_bot.py
slack_bot/slack_client_wrapper.py
slack_bot_wrapper.egg-info/PKG-INFO
slack_bot_wrapper.egg-info/SOURCES.txt
slack_bot_wrapper.egg-info/dependency_links.txt
slack_bot_wrapper.egg-info/not-zip-safe
slack_bot_wrapper.egg-info/requires.txt
slack_bot_wrapper.egg-info/top_level.txt