Metadata-Version: 1.1
Name: slack-bot-wrapper
Version: 0.0.2
Summary: Slack Bot Wrapper
Home-page: https://github.com/nicolastrres/slack-bot-wrapper
Author: Nicolas Agustin Torres
Author-email: nicolastrres@gmail.com
License: MIT
Keywords: slack bot communication automate tasks
Platform: UNKNOWN
Classifier: Development Status :: 3 - Alpha
Classifier: Intended Audience :: Developers
Classifier: License :: OSI Approved :: MIT License
Classifier: Programming Language :: Python :: 3.5
